auger/hub_api_client/__init__.py
auger/hub_api_client/hub_api_client.py
auger_hub_api_client-0.7.4.dist-info/LICENSE
auger_hub_api_client-0.7.4.dist-info/METADATA
auger_hub_api_client-0.7.4.dist-info/WHEEL
auger_hub_api_client-0.7.4.dist-info/top_level.txt
auger_hub_api_client-0.7.4.dist-info/RECORD
