Metadata-Version: 2.1
Name: auger-hub-api-client
Version: 0.7.4
Summary: API client for Auger Hub API
Home-page: https://github.com/deeplearninc/
Author: DeepLearn Inc.
Author-email: alex@dplrn.com
License: MIT
Platform: UNKNOWN
Requires-Dist: requests
Requires-Dist: beautifulsoup4
Requires-Dist: lxml
